ad_bs_converter/__init__.py
ad_bs_converter/constants.py
ad_bs_converter/converter.py
ad_bs_converter/domain.py
ad_bs_converter/exceptions.py
ad_bs_converter/py.typed
ad_bs_converter-1.2.3.dist-info/LICENSE
ad_bs_converter-1.2.3.dist-info/METADATA
ad_bs_converter-1.2.3.dist-info/WHEEL
ad_bs_converter-1.2.3.dist-info/entry_points.txt
ad_bs_converter-1.2.3.dist-info/top_level.txt
ad_bs_converter-1.2.3.dist-info/RECORD
