Metadata-Version: 2.2
Name: ad_bs_converter
Version: 1.2.3
Summary: A Python package to convert AD dates to BS dates.
Author-email: Aayush Dip Giri <giridip862101@gmail.com>
License: MIT License
Project-URL: Bug Tracker, https://github.com/invincibleaayu/ad_bs_converter/issues
Project-URL: Documentation, https://github.com/invincibleaayu/ad_bs_converter#readme
Project-URL: Source Code, https://github.com/invincibleaayu/ad_bs_converter
Keywords: date-converter,ad-to-bs,nepali-date
Classifier: License :: OSI Approved :: MIT License
Classifier: Programming Language :: Python :: 3
Classifier: Programming Language :: Python :: 3.13
Classifier: Operating System :: OS Independent
Requires-Python: >=3.13
License-File: LICENSE
Requires-Dist: pydantic>=2.10.6
Requires-Dist: setuptools>=76.0.0
Requires-Dist: twine>=6.1.0
